vbftool/__init__.py
vbftool/checksum.py
vbftool/options.py
vbftool/vbf.py
vbftool-1.0a0.dist-info/DESCRIPTION.rst
vbftool-1.0a0.dist-info/LICENSE.txt
vbftool-1.0a0.dist-info/METADATA
vbftool-1.0a0.dist-info/RECORD
vbftool-1.0a0.dist-info/WHEEL
vbftool-1.0a0.dist-info/metadata.json
vbftool-1.0a0.dist-info/top_level.txt
